pyse/__init__.py
pyse/pyse.py
pysetest-0.1.0.dist-info/METADATA
pysetest-0.1.0.dist-info/WHEEL
pysetest-0.1.0.dist-info/top_level.txt
pysetest-0.1.0.dist-info/RECORD
