Metadata-Version: 2.1
Name: pysetest
Version: 0.1.0
Summary: E2E 
Home-page: https://github.com/titanom/pysetest
Author: uhasker
Author-email: uhasker@protonmail.com
License: MIT
Requires-Dist: requests
